LICENSE
MANIFEST.in
README.md
mkdocs.yml
setup.py
adt/__init__.py
adt_decorators.egg-info/PKG-INFO
adt_decorators.egg-info/SOURCES.txt
adt_decorators.egg-info/dependency_links.txt
adt_decorators.egg-info/top_level.txt
docs/overview.md
docs/reference.md