Metadata-Version: 2.1
Name: adt-decorators
Version: 0.2.10
Summary: Algebraic Data Types via Class Decorators
Home-page: https://github.com/m0rphism/adt-decorators
Author: Hannes Saffrich
Author-email: saffrich@informatik.uni-freiburg.de
License: BSD 2-clause
Classifier: Programming Language :: Python :: 3.10
Classifier: Programming Language :: Python :: 3.11
License-File: LICENSE
